grumble/__init__.py
grumble-1.1.1.dist-info/AUTHORS
grumble-1.1.1.dist-info/LICENSE
grumble-1.1.1.dist-info/METADATA
grumble-1.1.1.dist-info/WHEEL
grumble-1.1.1.dist-info/top_level.txt
grumble-1.1.1.dist-info/RECORD
