Metadata-Version: 2.1
Name: grumble
Version: 1.1.1
Summary: For print debuggers drowning in print statements.
Author-email: Christian Hammond <christian@beanbaginc.com>
License: MIT
Project-URL: homepage, https://github.com/beanbaginc/grumble
Project-URL: documentation, https://github.com/beanbaginc/grumble
Project-URL: repository, https://github.com/beanbaginc/grumble
Keywords: debugging,console,logs
Classifier: Development Status :: 4 - Beta
Classifier: Environment :: Console
Classifier: Intended Audience :: Developers
Classifier: License :: OSI Approved :: MIT License
Classifier: Operating System :: OS Independent
Classifier: Programming Language :: Python
Classifier: Programming Language :: Python :: 3
Classifier: Programming Language :: Python :: 3.6
Classifier: Programming Language :: Python :: 3.7
Classifier: Programming Language :: Python :: 3.8
Classifier: Programming Language :: Python :: 3.9
Classifier: Programming Language :: Python :: 3.10
Classifier: Programming Language :: Python :: 3.11
Classifier: Topic :: Software Development
Classifier: Topic :: Software Development :: Libraries
Requires-Python: >=3.6
License-File: LICENSE
License-File: AUTHORS
